numpy_nn/__init__.py
numpy_nn/numpy_nn.py
numpy_nn/activations/ELU.py
numpy_nn/activations/LeakyReLU.py
numpy_nn/activations/ReLU.py
numpy_nn/activations/Sigmoid.py
numpy_nn/activations/Softmax.py
numpy_nn/activations/Swish.py
numpy_nn/activations/TanH.py
numpy_nn/activations/__init__.py
numpy_nn/layers/Layer.py
numpy_nn/layers/Neuron.py
numpy_nn/layers/__init__.py
numpy_nn/losses/BinaryCrossEntropyLoss.py
numpy_nn/losses/CrossEntropyLoss.py
numpy_nn/losses/MeanAbsoluteError.py
numpy_nn/losses/MeanSquaredError.py
numpy_nn/losses/__init__.py
numpy_nn/models/Model.py
numpy_nn/models/__init__.py
numpy_nn/optimizers/Adam.py
numpy_nn/optimizers/Momentum.py
numpy_nn/optimizers/RMSProp.py
numpy_nn/optimizers/SGD.py
numpy_nn/optimizers/__init__.py
numpy_nn-0.2.6.dist-info/AUTHORS.rst
numpy_nn-0.2.6.dist-info/LICENSE
numpy_nn-0.2.6.dist-info/METADATA
numpy_nn-0.2.6.dist-info/WHEEL
numpy_nn-0.2.6.dist-info/top_level.txt
numpy_nn-0.2.6.dist-info/RECORD
