Metadata-Version: 2.1
Name: numpy-nn
Version: 0.2.6
Summary: Numpy NN is a Deep Neural Network Package which is built on base Numpy operations. This project is under development and any contributions are welcome.
Home-page: https://github.com/rahuldshetty/numpy_nn
Author: Rahul D Shetty
Author-email: 35rahuldshetty@gmail.com
License: MIT license
Keywords: numpy_nn
Platform: UNKNOWN
Classifier: Development Status :: 2 - Pre-Alpha
Classifier: Intended Audience :: Developers
Classifier: License :: OSI Approved :: MIT License
Classifier: Natural Language :: English
Classifier: Programming Language :: Python :: 3
Classifier: Programming Language :: Python :: 3.5
Classifier: Programming Language :: Python :: 3.6
Classifier: Programming Language :: Python :: 3.7
Classifier: Programming Language :: Python :: 3.8
Requires-Python: >=3.5
